LICENSE.txt
MANIFEST.in
README.md
setup.py
rethinkengine/__init__.py
rethinkengine/connection.py
rethinkengine/document.py
rethinkengine/fields.py
rethinkengine/query_set.py
rethinkengine.egg-info/PKG-INFO
rethinkengine.egg-info/SOURCES.txt
rethinkengine.egg-info/dependency_links.txt
rethinkengine.egg-info/requires.txt
rethinkengine.egg-info/top_level.txt