Metadata-Version: 1.1
Name: rethinkengine
Version: 0.1.0
Summary: RethinkDB Object-Document Mapper
Home-page: https://github.com/bwind/rethinkengine
Author: Bas Wind
Author-email: mailtobwind@gmail.com
License: BSD
Download-URL: https://pypi.python.org/pypi/Propeller
Keywords: rethinkdb object-document mapper
Platform: UNKNOWN
Classifier: Development Status :: 3 - Alpha
Classifier: Intended Audience :: Developers
Classifier: License :: OSI Approved :: BSD License
Classifier: Topic :: Database
Classifier: Topic :: Software Development :: Libraries :: Python Modules
